{
  "applications": "*",
  "changelogDate": "20230409195737",
  "dto": "mapstruct",
  "embedded": false,
  "entityTableName": "association",
  "fields": [
    {
      "fieldName": "idAsso",
      "fieldType": "Integer",
      "fieldValidateRules": ["required", "unique"]
    },
    {
      "fieldName": "nomAsso",
      "fieldType": "String",
      "fieldValidateRules": ["required"]
    }
  ],
  "fluentMethods": true,
  "jpaMetamodelFiltering": false,
  "name": "Association",
  "pagination": "no",
  "readOnly": false,
  "relationships": [
    {
      "otherEntityName": "livreur",
      "otherEntityRelationshipName": "association",
      "relationshipName": "livreur",
      "relationshipType": "one-to-many"
    }
  ],
  "service": "serviceClass"
}
